musubi/__init__.py
musubi/async_crawl_content.py
musubi/async_crawl_link.py
musubi/crawl_content.py
musubi/crawl_link.py
musubi/pipeline.py
musubi/agent/__init__.py
musubi/agent/agents.py
musubi/agent/models.py
musubi/agent/system_prompt.py
musubi/agent/actions/__init__.py
musubi/agent/actions/general_tool_actions.py
musubi/agent/actions/pipeline_tool_actions.py
musubi/agent/actions/scheduler_actions.py
musubi/commands/__init__.py
musubi/commands/agent.py
musubi/commands/analyze.py
musubi/commands/crawl.py
musubi/commands/env.py
musubi/commands/get.py
musubi/commands/musubi_cli.py
musubi/commands/pipeline.py
musubi/commands/start.py
musubi/scheduler/__init__.py
musubi/scheduler/controller.py
musubi/scheduler/dataformat.py
musubi/scheduler/notification.py
musubi/scheduler/scheduler.py
musubi/scheduler/tasks.py
musubi/utils/__init__.py
musubi/utils/analyze.py
musubi/utils/deduplicate.py
musubi/utils/env.py
musubi/utils/helpers.py
musubi_scrape-1.0.2.dist-info/METADATA
musubi_scrape-1.0.2.dist-info/WHEEL
musubi_scrape-1.0.2.dist-info/licenses/LICENSE
musubi_scrape-1.0.2.dist-info/RECORD
