Metadata-Version: 2.4
Name: musubi-scrape
Version: 1.0.2
Summary: A convenient crawling package for collecting web data.
Project-URL: Homepage, https://github.com/Musubi-ai/Musubi
Project-URL: Repository, https://github.com/Musubi-ai/Musubi
Author-email: Lung-Chuan Chen <blaze7451@gmail.com>
License:                                  Apache License
License-File: LICENSE
Requires-Python: <4.0,>=3.9
Requires-Dist: aiohttp<4.0.0,>=3.11.12
Requires-Dist: anthropic<0.46.0,>=0.45.2
Requires-Dist: apscheduler<4.0.0,>=3.11.0
Requires-Dist: beautifulsoup4<5.0.0,>=4.13.3
Requires-Dist: fastapi>=0.117.1
Requires-Dist: groq<0.19.0,>=0.18.0
Requires-Dist: huggingface-hub<0.29.0,>=0.28.1
Requires-Dist: loguru<0.8.0,>=0.7.3
Requires-Dist: openai<2.0.0,>=1.61.1
Requires-Dist: orjson<4.0.0,>=3.11.3
Requires-Dist: pandas<3.0.0,>=2.2.3
Requires-Dist: pyarrow<20.0.0,>=19.0.0
Requires-Dist: pymupdf4llm<0.0.18,>=0.0.17
Requires-Dist: pymupdf<2.0.0,>=1.25.2
Requires-Dist: python-dotenv<2.0.0,>=1.0.1
Requires-Dist: requests<3.0.0,>=2.32.3
Requires-Dist: rich<14.0.0,>=13.9.4
Requires-Dist: selenium<5.0.0,>=4.28.1
Requires-Dist: tqdm<5.0.0,>=4.67.1
Requires-Dist: trafilatura==2.0.0
Requires-Dist: uvicorn>=0.37.0
Provides-Extra: test
Requires-Dist: pytest; extra == 'test'
